odoo/addons/account_invoice_show_currency_rate/README.rst
odoo/addons/account_invoice_show_currency_rate/__init__.py
odoo/addons/account_invoice_show_currency_rate/__manifest__.py
odoo/addons/account_invoice_show_currency_rate/i18n/account_invoice_show_currency_rate.pot
odoo/addons/account_invoice_show_currency_rate/i18n/es.po
odoo/addons/account_invoice_show_currency_rate/i18n/it.po
odoo/addons/account_invoice_show_currency_rate/models/__init__.py
odoo/addons/account_invoice_show_currency_rate/models/account_move.py
odoo/addons/account_invoice_show_currency_rate/readme/CONFIGURE.md
odoo/addons/account_invoice_show_currency_rate/readme/CONTRIBUTORS.md
odoo/addons/account_invoice_show_currency_rate/readme/DESCRIPTION.md
odoo/addons/account_invoice_show_currency_rate/readme/USAGE.md
odoo/addons/account_invoice_show_currency_rate/static/description/icon.png
odoo/addons/account_invoice_show_currency_rate/static/description/index.html
odoo/addons/account_invoice_show_currency_rate/tests/__init__.py
odoo/addons/account_invoice_show_currency_rate/tests/test_account_move.py
odoo/addons/account_invoice_show_currency_rate/views/account_move_view.xml
odoo_addon_account_invoice_show_currency_rate-18.0.1.0.1.dist-info/METADATA
odoo_addon_account_invoice_show_currency_rate-18.0.1.0.1.dist-info/WHEEL
odoo_addon_account_invoice_show_currency_rate-18.0.1.0.1.dist-info/top_level.txt
odoo_addon_account_invoice_show_currency_rate-18.0.1.0.1.dist-info/RECORD
